[1,["1437LfQVZGK5/Z0qEvAa5E@f9941","acn3Z80jRPH5fiQ8+qGH13@f9941","627s8b6gxImI+78HB6g27u@f9941","6dR/heT7dEjpegHfquwv/s@f9941","1437LfQVZGK5/Z0qEvAa5E@6c48a","f627FXi2FObZT7G1STZzH7","627s8b6gxImI+78HB6g27u@6c48a","6dR/heT7dEjpegHfquwv/s@6c48a","acn3Z80jRPH5fiQ8+qGH13@6c48a","17eJ1l9QVPErtIkpOucUQc@6c48a","e7Dg+PFbJG2780Mk9v2tNv"],["node","_spriteFrame","_textureSource","target","source","root","data","_parent","prefabRootNode","asset","initPos","targetPos","enterPos","_skeletonData"],[["cc.Node",["_name","_layer","_objFlags","__editorExtras__","_prefab","_components","_children","_parent","_lpos","_lscale"],-1,4,9,2,1,5,5],"cc.SpriteFrame",["cc.UITransform",["node","__prefab","_contentSize","_anchorPoint"],3,1,4,5,5],["cc.Prefab",["_name"],2],["97133pgRxhOxo6ZBVhGgCI9",["node","__prefab"],3,1,4],["cc.CompPrefabInfo",["fileId"],2],["cc.UIOpacity",["node","__prefab"],3,1,4],["cc.PrefabInfo",["fileId","instance","root","asset","targetOverrides","nestedPrefabInstanceRoots"],1,1,1,9,2],["cc.PrefabInfo",["fileId","instance","targetOverrides","nestedPrefabInstanceRoots","root","asset"],-1,1,1],["cc.PrefabInfo",["fileId","targetOverrides","nestedPrefabInstanceRoots","root","instance","asset"],0,1,4,6],["cc.TargetOverrideInfo",["propertyPath","source","sourceInfo","target","targetInfo"],2,1,4,1,4],["cc.TargetInfo",["localID"],2],["cc.PrefabInstance",["fileId","prefabRootNode","propertyOverrides"],2,1,9],["CCPropertyOverrideInfo",["value","propertyPath","targetInfo"],1,4],["CCPropertyOverrideInfo",["propertyPath","targetInfo","value"],2,4,8],["cc.Sprite",["node","__prefab","_spriteFrame"],3,1,4,6],["sp.SkeletonData",["_name","_native","_atlasText","textureNames","textures"],-1,3],["e8902K0MPJO9Lh2mPJ4GKGY",["node","__prefab","enterPos","targetPos","initPos"],3,1,4,1,1,1],["cc.BoxCollider2D",["node","__prefab","_offset","_size"],3,1,4,5,5],["sp.Skeleton",["defaultSkin","defaultAnimation","_preCacheMode","node","__prefab","_skeletonData"],0,1,4,6]],[[5,0,2],[8,0,1,2,3,4,5,5],[2,0,1,2,1],[0,0,1,7,5,4,8,3],[11,0,2],[15,0,1,2,1],[6,0,1,1],[10,0,1,2,3,4,2],[14,0,1,2,2],[3,0,2],[0,0,1,7,6,5,4,3],[2,0,1,1],[13,0,1,2,3],[0,0,1,6,5,4,9,3],[0,0,1,6,5,4,3],[0,2,3,4,3],[0,0,1,6,5,4,8,3],[0,0,1,7,5,4,3],[4,0,1,1],[2,0,1,2,3,1],[7,0,1,2,3,4,5,3],[9,0,1,2,3,4,5,4],[12,0,1,2,2],[16,0,1,2,3,4,5],[17,0,1,2,3,4,1],[18,0,1,2,3,1],[19,0,1,2,3,4,5,4]],[[[{"name":"副本场景1","rect":{"x":0,"y":0,"width":750,"height":750},"offset":{"x":0,"y":0},"originalSize":{"width":750,"height":750},"rotated":false,"capInsets":[0,0,0,0],"vertices":{"rawPosition":[-375,-375,0,375,-375,0,-375,375,0,375,375,0],"indexes":[0,1,2,2,1,3],"uv":[0,750,750,750,0,0,750,0],"nuv":[0,0,1,0,0,1,1,1],"minPos":{"x":-375,"y":-375,"z":0},"maxPos":{"x":375,"y":375,"z":0}},"packable":true,"pixelsToUnit":100,"pivot":{"x":0.5,"y":0.5},"meshType":0}],[1],0,[0],[2],[4]],[[[9,"森林_2"],[13,"森林_2",1,[-12],[[18,-9,[0,"abPwWpq31Mfof6KWq5S3w/"]],[6,-10,[0,"3fVtWmRtNEy79HmTfx2ENt"]],[2,-11,[0,"80Q6au6HVBCJyxa3ICX31T"],[5,5016,2508]]],[20,"76Q3inZFpPIpeq7QmR9BSs",null,-8,0,[[7,["enterPos"],-3,[4,["a2bNZwQkNPDJFePNc4YlVO"]],-2,[4,["b9HMMYfENDZ5G82TCyne8x"]]],[7,["targetPos"],-5,[4,["a2bNZwQkNPDJFePNc4YlVO"]],-4,[4,["9fN2GX6AZHp4AQrINANK4I"]]],[7,["initPos"],-7,[4,["a2bNZwQkNPDJFePNc4YlVO"]],-6,[4,["64S87AlYpPY6VS+Bq4ZX/M"]]]],[-1]],[1,1,1,2]],[14,"1",1,[-15,-16,-17,-18,-19,-20,-21,-22],[[6,-13,[0,"25ZYA7qvpJe7zDFPL1WM9s"]],[2,-14,[0,"bbn+4KiCpM6Zxxi7PvA+pQ"],[5,0,0]]],[1,"d4hscgcUVHh6JCwVnWFis+",null,null,null,1,0]],[15,0,{},[21,"QQNMhYPyq/9dhFwNATDp/k",null,null,-24,[22,"0aXcVA8IJPorjvioXGZpps",-23,[[12,"传送门",["_name"],[4,["fd+7FhJD9ADZZrbriUcvfR"]]],[8,["_lpos"],[4,["fd+7FhJD9ADZZrbriUcvfR"]],[1,0,0,0]],[8,["_lrot"],[4,["fd+7FhJD9ADZZrbriUcvfR"]],[3,0,0,0,1]],[8,["_euler"],[4,["fd+7FhJD9ADZZrbriUcvfR"]],[1,0,0,0]],[12,1,["targetMapId"],[4,["a2bNZwQkNPDJFePNc4YlVO"]]]]],8]],[10,"mapElementRoot",1,1,[-26,3],[[11,-25,[0,"5diEpasIpMoIqc4bve20Wr"]]],[1,"50VY7JtPNJ0qP36Vo94uUp",null,null,null,1,0]],[10,"bg",1,4,[2],[[6,-27,[0,"c37pBTNxNDiZQm3J+PHH+B"]],[2,-28,[0,"bd+um6OLZFHr9dhVcXhFEF"],[5,0,0]]],[1,"9bj5llCEJLkYXwBf8WIBWA",null,null,null,1,0]],[3,"副本场景1",1,2,[[2,-29,[0,"5bXzKNzB1O/aS1oiSdqXHH"],[5,750,750]],[5,-30,[0,"66vtWXpHhJgJsCiqjQC9qz"],0]],[1,"8bBIgLhJNJyoThELSkBKCz",null,null,null,1,0],[1,-375,375,0]],[3,"副本场景2",1,2,[[2,-31,[0,"2aRRlDd7FKv59Zu1UrKJex"],[5,750,750]],[5,-32,[0,"ae1uur2VFI4bd+vD605IxJ"],1]],[1,"09G0O0ZSVMULGuXXf/WCIC",null,null,null,1,0],[1,375,375,0]],[3,"副本场景3",1,2,[[2,-33,[0,"bemAW9c+5D26i38ujP62h1"],[5,750,750]],[5,-34,[0,"fd5BU7FFdLibyUOeNzZcce"],2]],[1,"cd0pH8/ylHh78f8Ra3T67G",null,null,null,1,0],[1,-375,-375,0]],[3,"副本场景4",1,2,[[2,-35,[0,"c9hl84VDpFHKpNJT3Id/wz"],[5,750,750]],[5,-36,[0,"f2zwMDhQlPTp8m+QCdOGFE"],3]],[1,"8bIgXGCCxLS6hrXe/vBEyq",null,null,null,1,0],[1,375,-375,0]],[3,"副本场景5",1,2,[[2,-37,[0,"38/RgdOf5BqK7WHXXnx/Yy"],[5,750,750]],[5,-38,[0,"ddnBLRXVxOuanHPmBSYc35"],4]],[1,"c3RmSoCm9Kf62VB1HZgtxY",null,null,null,1,0],[1,-375,-1123.358,0]],[3,"副本场景6",1,2,[[2,-39,[0,"13vXsKlnNBqqgeFRxr4xa2"],[5,750,750]],[5,-40,[0,"61dNGpzGFPKq8JWrNfMHro"],5]],[1,"a2QOUTbIZDD7HLvw+qULW6",null,null,null,1,0],[1,375,-1124.821,0]],[3,"副本场景7",1,2,[[2,-41,[0,"83hEtRZdROcpVsYeIIv/ie"],[5,750,750]],[5,-42,[0,"d4XaGD+0BKYKafi4dUPgcb"],6]],[1,"0cCH98Fn1AaLryfIyDMHJV",null,null,null,1,0],[1,-375,1124.702,0]],[3,"副本场景8",1,2,[[2,-43,[0,"33oGmg+mJODrEuDZWrWpph"],[5,750,750]],[5,-44,[0,"e7Nl0GWfJLg64no+sWA1i6"],7]],[1,"574PFNgMpB1p5GnzUBvd0L",null,null,null,1,0],[1,375,1124.702,0]]],0,[0,-1,3,0,3,3,0,4,3,0,3,3,0,4,3,0,3,3,0,4,3,0,5,1,0,0,1,0,0,1,0,0,1,0,-1,4,0,0,2,0,0,2,0,-1,6,0,-2,7,0,-3,8,0,-4,9,0,-5,10,0,-6,11,0,-7,12,0,-8,13,0,8,4,0,5,3,0,0,4,0,-1,5,0,0,5,0,0,5,0,0,6,0,0,6,0,0,7,0,0,7,0,0,8,0,0,8,0,0,9,0,0,9,0,0,10,0,0,10,0,0,11,0,0,11,0,0,12,0,0,12,0,0,13,0,0,13,0,6,1,2,7,5,3,7,4,44],[0,0,0,0,0,0,0,0,0],[1,1,1,1,1,1,1,1,9],[0,1,2,3,0,1,2,3,5]],[[{"name":"副本场景3","rect":{"x":0,"y":0,"width":750,"height":750},"offset":{"x":0,"y":0},"originalSize":{"width":750,"height":750},"rotated":false,"capInsets":[0,0,0,0],"vertices":{"rawPosition":[-375,-375,0,375,-375,0,-375,375,0,375,375,0],"indexes":[0,1,2,2,1,3],"uv":[0,750,750,750,0,0,750,0],"nuv":[0,0,1,0,0,1,1,1],"minPos":{"x":-375,"y":-375,"z":0},"maxPos":{"x":375,"y":375,"z":0}},"packable":true,"pixelsToUnit":100,"pivot":{"x":0.5,"y":0.5},"meshType":0}],[1],0,[0],[2],[6]],[[{"name":"副本场景4","rect":{"x":0,"y":0,"width":750,"height":750},"offset":{"x":0,"y":0},"originalSize":{"width":750,"height":750},"rotated":false,"capInsets":[0,0,0,0],"vertices":{"rawPosition":[-375,-375,0,375,-375,0,-375,375,0,375,375,0],"indexes":[0,1,2,2,1,3],"uv":[0,750,750,750,0,0,750,0],"nuv":[0,0,1,0,0,1,1,1],"minPos":{"x":-375,"y":-375,"z":0},"maxPos":{"x":375,"y":375,"z":0}},"packable":true,"pixelsToUnit":100,"pivot":{"x":0.5,"y":0.5},"meshType":0}],[1],0,[0],[2],[7]],[[{"name":"副本场景2","rect":{"x":0,"y":0,"width":750,"height":750},"offset":{"x":0,"y":0},"originalSize":{"width":750,"height":750},"rotated":false,"capInsets":[0,0,0,0],"vertices":{"rawPosition":[-375,-375,0,375,-375,0,-375,375,0,375,375,0],"indexes":[0,1,2,2,1,3],"uv":[0,750,750,750,0,0,750,0],"nuv":[0,0,1,0,0,1,1,1],"minPos":{"x":-375,"y":-375,"z":0},"maxPos":{"x":375,"y":375,"z":0}},"packable":true,"pixelsToUnit":100,"pivot":{"x":0.5,"y":0.5},"meshType":0}],[1],0,[0],[2],[8]],[[[23,"fz_e70e0f8f",".bin","\r\nfz.png\r\nsize: 974,459\r\nformat: RGBA8888\r\nfilter: Linear,Linear\r\nrepeat: none\r\nFW_000\r\n  rotate: true\r\n  xy: 910, 349\r\n  size: 48, 60\r\n  orig: 85, 85\r\n  offset: 17, 13\r\n  index: -1\r\nFW_001\r\n  rotate: false\r\n  xy: 881, 26\r\n  size: 44, 56\r\n  orig: 85, 85\r\n  offset: 21, 14\r\n  index: -1\r\nFW_002\r\n  rotate: false\r\n  xy: 658, 2\r\n  size: 49, 52\r\n  orig: 85, 85\r\n  offset: 20, 17\r\n  index: -1\r\nFW_003\r\n  rotate: false\r\n  xy: 891, 240\r\n  size: 45, 56\r\n  orig: 85, 85\r\n  offset: 19, 14\r\n  index: -1\r\nFW_004\r\n  rotate: true\r\n  xy: 2, 2\r\n  size: 42, 51\r\n  orig: 85, 85\r\n  offset: 24, 17\r\n  index: -1\r\nFW_005\r\n  rotate: false\r\n  xy: 891, 184\r\n  size: 45, 54\r\n  orig: 85, 85\r\n  offset: 23, 16\r\n  index: -1\r\nFW_006\r\n  rotate: true\r\n  xy: 492, 2\r\n  size: 44, 57\r\n  orig: 85, 85\r\n  offset: 22, 14\r\n  index: -1\r\nFW_007\r\n  rotate: true\r\n  xy: 429, 2\r\n  size: 44, 61\r\n  orig: 85, 85\r\n  offset: 22, 11\r\n  index: -1\r\na\r\n  rotate: false\r\n  xy: 2, 46\r\n  size: 425, 411\r\n  orig: 447, 441\r\n  offset: 19, 21\r\n  index: -1\r\na01\r\n  rotate: true\r\n  xy: 774, 128\r\n  size: 31, 82\r\n  orig: 46, 92\r\n  offset: 6, 4\r\n  index: -1\r\na02\r\n  rotate: false\r\n  xy: 741, 128\r\n  size: 31, 84\r\n  orig: 46, 92\r\n  offset: 6, 4\r\n  index: -1\r\na03\r\n  rotate: true\r\n  xy: 701, 94\r\n  size: 32, 84\r\n  orig: 46, 92\r\n  offset: 6, 4\r\n  index: -1\r\na04\r\n  rotate: true\r\n  xy: 791, 59\r\n  size: 33, 84\r\n  orig: 46, 92\r\n  offset: 5, 4\r\n  index: -1\r\na05\r\n  rotate: true\r\n  xy: 823, 383\r\n  size: 34, 85\r\n  orig: 46, 92\r\n  offset: 4, 3\r\n  index: -1\r\na06\r\n  rotate: false\r\n  xy: 727, 214\r\n  size: 35, 85\r\n  orig: 46, 92\r\n  offset: 4, 3\r\n  index: -1\r\na07\r\n  rotate: true\r\n  xy: 823, 307\r\n  size: 35, 85\r\n  orig: 46, 92\r\n  offset: 4, 3\r\n  index: -1\r\na08\r\n  rotate: true\r\n  xy: 617, 56\r\n  size: 36, 85\r\n  orig: 46, 92\r\n  offset: 4, 3\r\n  index: -1\r\na09\r\n  rotate: true\r\n  xy: 704, 56\r\n  size: 36, 85\r\n  orig: 46, 92\r\n  offset: 4, 3\r\n  index: -1\r\na10\r\n  rotate: true\r\n  xy: 617, 94\r\n  size: 36, 82\r\n  orig: 46, 92\r\n  offset: 4, 3\r\n  index: -1\r\na11\r\n  rotate: false\r\n  xy: 701, 129\r\n  size: 38, 83\r\n  orig: 46, 92\r\n  offset: 3, 3\r\n  index: -1\r\na12\r\n  rotate: true\r\n  xy: 709, 16\r\n  size: 38, 83\r\n  orig: 46, 92\r\n  offset: 3, 3\r\n  index: -1\r\na13\r\n  rotate: false\r\n  xy: 764, 245\r\n  size: 38, 83\r\n  orig: 46, 92\r\n  offset: 3, 3\r\n  index: -1\r\na14\r\n  rotate: true\r\n  xy: 823, 419\r\n  size: 38, 85\r\n  orig: 46, 92\r\n  offset: 3, 3\r\n  index: -1\r\na15\r\n  rotate: true\r\n  xy: 55, 5\r\n  size: 39, 84\r\n  orig: 46, 92\r\n  offset: 2, 3\r\n  index: -1\r\na16\r\n  rotate: false\r\n  xy: 686, 214\r\n  size: 39, 85\r\n  orig: 46, 92\r\n  offset: 2, 3\r\n  index: -1\r\na17\r\n  rotate: true\r\n  xy: 141, 6\r\n  size: 38, 85\r\n  orig: 46, 92\r\n  offset: 3, 2\r\n  index: -1\r\na18\r\n  rotate: true\r\n  xy: 228, 6\r\n  size: 38, 85\r\n  orig: 46, 92\r\n  offset: 3, 3\r\n  index: -1\r\na19\r\n  rotate: true\r\n  xy: 315, 7\r\n  size: 37, 86\r\n  orig: 46, 92\r\n  offset: 4, 3\r\n  index: -1\r\na20\r\n  rotate: true\r\n  xy: 823, 344\r\n  size: 37, 85\r\n  orig: 46, 92\r\n  offset: 4, 3\r\n  index: -1\r\na21\r\n  rotate: true\r\n  xy: 804, 270\r\n  size: 35, 85\r\n  orig: 46, 92\r\n  offset: 5, 3\r\n  index: -1\r\na22\r\n  rotate: true\r\n  xy: 804, 233\r\n  size: 35, 85\r\n  orig: 46, 92\r\n  offset: 5, 3\r\n  index: -1\r\na23\r\n  rotate: true\r\n  xy: 794, 196\r\n  size: 35, 85\r\n  orig: 46, 92\r\n  offset: 5, 3\r\n  index: -1\r\na24\r\n  rotate: false\r\n  xy: 938, 211\r\n  size: 34, 85\r\n  orig: 46, 92\r\n  offset: 5, 3\r\n  index: -1\r\na25\r\n  rotate: true\r\n  xy: 774, 161\r\n  size: 33, 85\r\n  orig: 46, 92\r\n  offset: 5, 3\r\n  index: -1\r\na26\r\n  rotate: true\r\n  xy: 794, 24\r\n  size: 33, 85\r\n  orig: 46, 92\r\n  offset: 5, 3\r\n  index: -1\r\na27\r\n  rotate: true\r\n  xy: 861, 149\r\n  size: 33, 85\r\n  orig: 46, 92\r\n  offset: 4, 2\r\n  index: -1\r\na28\r\n  rotate: true\r\n  xy: 787, 94\r\n  size: 32, 85\r\n  orig: 46, 92\r\n  offset: 4, 3\r\n  index: -1\r\na29\r\n  rotate: true\r\n  xy: 874, 115\r\n  size: 32, 82\r\n  orig: 46, 92\r\n  offset: 4, 4\r\n  index: -1\r\na30\r\n  rotate: true\r\n  xy: 877, 84\r\n  size: 29, 82\r\n  orig: 46, 92\r\n  offset: 7, 4\r\n  index: -1\r\nquan_000\r\n  rotate: false\r\n  xy: 686, 379\r\n  size: 74, 78\r\n  orig: 96, 96\r\n  offset: 12, 9\r\n  index: -1\r\nquan_001\r\n  rotate: false\r\n  xy: 429, 122\r\n  size: 76, 77\r\n  orig: 96, 96\r\n  offset: 11, 9\r\n  index: -1\r\nquan_002\r\n  rotate: false\r\n  xy: 429, 48\r\n  size: 77, 72\r\n  orig: 96, 96\r\n  offset: 10, 12\r\n  index: -1\r\nquan_003\r\n  rotate: true\r\n  xy: 686, 301\r\n  size: 76, 73\r\n  orig: 96, 96\r\n  offset: 11, 11\r\n  index: -1\r\nquan_004\r\n  rotate: false\r\n  xy: 507, 122\r\n  size: 74, 77\r\n  orig: 96, 96\r\n  offset: 13, 9\r\n  index: -1\r\nquan_005\r\n  rotate: false\r\n  xy: 762, 330\r\n  size: 59, 53\r\n  orig: 96, 96\r\n  offset: 19, 21\r\n  index: -1\r\nquan_006\r\n  rotate: false\r\n  xy: 910, 298\r\n  size: 58, 49\r\n  orig: 96, 96\r\n  offset: 21, 23\r\n  index: -1\r\nquan_007\r\n  rotate: true\r\n  xy: 567, 56\r\n  size: 64, 48\r\n  orig: 96, 96\r\n  offset: 20, 22\r\n  index: -1\r\nquan_008\r\n  rotate: true\r\n  xy: 644, 132\r\n  size: 67, 55\r\n  orig: 96, 96\r\n  offset: 18, 20\r\n  index: -1\r\nquan_009\r\n  rotate: true\r\n  xy: 910, 399\r\n  size: 58, 62\r\n  orig: 96, 96\r\n  offset: 28, 17\r\n  index: -1\r\nquan_010\r\n  rotate: false\r\n  xy: 762, 385\r\n  size: 59, 72\r\n  orig: 96, 96\r\n  offset: 27, 12\r\n  index: -1\r\nquan_011\r\n  rotate: false\r\n  xy: 583, 133\r\n  size: 59, 66\r\n  orig: 96, 96\r\n  offset: 27, 15\r\n  index: -1\r\nquan_012\r\n  rotate: false\r\n  xy: 508, 54\r\n  size: 57, 66\r\n  orig: 96, 96\r\n  offset: 27, 15\r\n  index: -1\r\nquan_013\r\n  rotate: true\r\n  xy: 598, 2\r\n  size: 52, 58\r\n  orig: 96, 96\r\n  offset: 30, 20\r\n  index: -1\r\nquan_014\r\n  rotate: false\r\n  xy: 551, 2\r\n  size: 45, 50\r\n  orig: 96, 96\r\n  offset: 36, 25\r\n  index: -1\r\nquan_015\r\n  rotate: false\r\n  xy: 709, 4\r\n  size: 41, 10\r\n  orig: 96, 96\r\n  offset: 38, 38\r\n  index: -1\r\ny\r\n  rotate: false\r\n  xy: 429, 201\r\n  size: 255, 256\r\n  orig: 256, 256\r\n  offset: 0, 0\r\n  index: -1\r\n",["fz.png"],[0]],-1],0,0,[0],[-1],[9]],[[[9,"传送门"],[16,"传送门",1,[-9,-10,-11,-12],[[6,-2,[0,"a0lKr/k5lPu4Ui0IkDb7P8"]],[11,-3,[0,"351zQ6v1hPMJqcCevyRERi"]],[24,-7,[0,"a2bNZwQkNPDJFePNc4YlVO"],-6,-5,-4],[25,-8,[0,"b3fTgT3LhLxa0JmCOC+4gT"],[0,-4.1,-8.2],[5,50,50]]],[1,"fd+7FhJD9ADZZrbriUcvfR",null,null,null,-1,0],[1,-1145.125,1101.68,0]],[3,"正下方",1,1,[[6,-13,[0,"ffTK52EvJEGqBwldu5aI4k"]],[2,-14,[0,"61Q45Ip4xM9I8QS4rPPe1b"],[5,0,0]]],[1,"b9HMMYfENDZ5G82TCyne8x",null,null,null,1,0],[1,0,-123.841,0]],[17,"入口",1,1,[[6,-15,[0,"0a2z3kEbtLA6qSDvRxqyaR"]],[2,-16,[0,"90BiG+M8JMC6z3pcINKDnb"],[5,0,0]]],[1,"9fN2GX6AZHp4AQrINANK4I",null,null,null,1,0]],[3,"出生点",1,1,[[6,-17,[0,"cbKgN9ibBOhJkpojsEaI+Q"]],[2,-18,[0,"96XSzk8+REIoGdiQUAmPww"],[5,0,0]]],[1,"64S87AlYpPY6VS+Bq4ZX/M",null,null,null,1,0],[1,0,-265.516,0]],[3,"guang",1,1,[[19,-19,[0,"23lL7h5d1GELiLeVnazeSz"],[5,577.1321411132812,552.72607421875],[0,0.5000000528779736,0.17805634006871127]],[26,"default","animation",0,-20,[0,"4e85o5CQ1Emqmzg0uoA9b8"],0]],[1,"3azmViL/FNxLWW0lQCcBlJ",null,null,null,1,0],[1,0,-44.327,0]]],0,[0,5,1,0,0,1,0,0,1,0,10,4,0,11,3,0,12,2,0,0,1,0,0,1,0,-1,5,0,-2,2,0,-3,3,0,-4,4,0,0,2,0,0,2,0,0,3,0,0,3,0,0,4,0,0,4,0,0,5,0,0,5,0,6,1,20],[0],[13],[10]]]]
