[1,["655YPgYQ5Bjoi1koMH26u2@6c48a"],["_textureSource"],["cc.SpriteFrame","cc.SpriteAtlas"],0,[[[{"name":"乱斗道具","spriteFrames":["袋1-3","1aHs1pKdhMX59HgR/kWUzf@0164f","6-1","1aHs1pKdhMX59HgR/kWUzf@06a39","5-3","1aHs1pKdhMX59HgR/kWUzf@0eb4b","5-1","1aHs1pKdhMX59HgR/kWUzf@11f48","1-3","1aHs1pKdhMX59HgR/kWUzf@17483","1-5","1aHs1pKdhMX59HgR/kWUzf@1976c","7-6","1aHs1pKdhMX59HgR/kWUzf@1b1ca","6-2","1aHs1pKdhMX59HgR/kWUzf@1d064","2-5","1aHs1pKdhMX59HgR/kWUzf@242f7","4-2","1aHs1pKdhMX59HgR/kWUzf@276a3","袋1-2","1aHs1pKdhMX59HgR/kWUzf@30f03","盲盒","1aHs1pKdhMX59HgR/kWUzf@32c18","2-2","1aHs1pKdhMX59HgR/kWUzf@34092","5-6","1aHs1pKdhMX59HgR/kWUzf@35377","1-4","1aHs1pKdhMX59HgR/kWUzf@3931e","7-5","1aHs1pKdhMX59HgR/kWUzf@3fc33","1-6","1aHs1pKdhMX59HgR/kWUzf@48bb5","4-3","1aHs1pKdhMX59HgR/kWUzf@4f8e2","4-5","1aHs1pKdhMX59HgR/kWUzf@578ef","3-5","1aHs1pKdhMX59HgR/kWUzf@5cc38","5-4","1aHs1pKdhMX59HgR/kWUzf@61ab8","5-5","1aHs1pKdhMX59HgR/kWUzf@6660d","2-4","1aHs1pKdhMX59HgR/kWUzf@6c74c","7-2","1aHs1pKdhMX59HgR/kWUzf@6cae1","4-4","1aHs1pKdhMX59HgR/kWUzf@6f5c9","3-3","1aHs1pKdhMX59HgR/kWUzf@776a0","4-1","1aHs1pKdhMX59HgR/kWUzf@7a622","袋1-1","1aHs1pKdhMX59HgR/kWUzf@83e06","2-1","1aHs1pKdhMX59HgR/kWUzf@8598a","1-2","1aHs1pKdhMX59HgR/kWUzf@9cc72","7-1","1aHs1pKdhMX59HgR/kWUzf@a9f06","6-4","1aHs1pKdhMX59HgR/kWUzf@adbaa","袋1-6","1aHs1pKdhMX59HgR/kWUzf@af0de","3-2","1aHs1pKdhMX59HgR/kWUzf@b393c","3-4","1aHs1pKdhMX59HgR/kWUzf@ba04b","4-6","1aHs1pKdhMX59HgR/kWUzf@bc33e","2-3","1aHs1pKdhMX59HgR/kWUzf@c3c77","袋1-4","1aHs1pKdhMX59HgR/kWUzf@c522f","3-1","1aHs1pKdhMX59HgR/kWUzf@cbaef","3-6","1aHs1pKdhMX59HgR/kWUzf@d01ff","7-3","1aHs1pKdhMX59HgR/kWUzf@d2abb","2-6","1aHs1pKdhMX59HgR/kWUzf@d41e4","7-4","1aHs1pKdhMX59HgR/kWUzf@db748","5-2","1aHs1pKdhMX59HgR/kWUzf@dfed3","6-6","1aHs1pKdhMX59HgR/kWUzf@e14d4","袋1-5","1aHs1pKdhMX59HgR/kWUzf@e5fa4","1-1","1aHs1pKdhMX59HgR/kWUzf@e6981","6-3","1aHs1pKdhMX59HgR/kWUzf@f68a2","6-5","1aHs1pKdhMX59HgR/kWUzf@f9ceb"]}],[1],0,[],[],[]],[[{"name":"袋1-3","rect":{"x":309,"y":491,"width":71,"height":134},"offset":{"x":0,"y":0},"originalSize":{"width":71,"height":134},"rotated":false,"capInsets":[0,0,0,0],"vertices":{"rawPosition":[],"indexes":[],"uv":[],"nuv":[],"minPos":{"x":0,"y":0,"z":0},"maxPos":{"x":0,"y":0,"z":0}},"packable":true,"pixelsToUnit":100,"pivot":{"x":0.5,"y":0.5},"meshType":0}],[0],0,[0],[0],[0]],[[{"name":"6-1","rect":{"x":251,"y":107,"width":84,"height":50},"offset":{"x":0,"y":0},"originalSize":{"width":84,"height":50},"rotated":true,"capInsets":[0,0,0,0],"vertices":{"rawPosition":[],"indexes":[],"uv":[],"nuv":[],"minPos":{"x":0,"y":0,"z":0},"maxPos":{"x":0,"y":0,"z":0}},"packable":true,"pixelsToUnit":100,"pivot":{"x":0.5,"y":0.5},"meshType":0}],[0],0,[0],[0],[0]],[[{"name":"5-3","rect":{"x":396,"y":1107,"width":98,"height":100},"offset":{"x":0,"y":0},"originalSize":{"width":98,"height":100},"rotated":false,"capInsets":[0,0,0,0],"vertices":{"rawPosition":[],"indexes":[],"uv":[],"nuv":[],"minPos":{"x":0,"y":0,"z":0},"maxPos":{"x":0,"y":0,"z":0}},"packable":true,"pixelsToUnit":100,"pivot":{"x":0.5,"y":0.5},"meshType":0}],[0],0,[0],[0],[0]],[[{"name":"5-1","rect":{"x":370,"y":681,"width":95,"height":69},"offset":{"x":0,"y":0},"originalSize":{"width":95,"height":69},"rotated":false,"capInsets":[0,0,0,0],"vertices":{"rawPosition":[],"indexes":[],"uv":[],"nuv":[],"minPos":{"x":0,"y":0,"z":0},"maxPos":{"x":0,"y":0,"z":0}},"packable":true,"pixelsToUnit":100,"pivot":{"x":0.5,"y":0.5},"meshType":0}],[0],0,[0],[0],[0]],[[{"name":"1-3","rect":{"x":1,"y":470,"width":251,"height":71},"offset":{"x":0,"y":0},"originalSize":{"width":251,"height":71},"rotated":true,"capInsets":[0,0,0,0],"vertices":{"rawPosition":[],"indexes":[],"uv":[],"nuv":[],"minPos":{"x":0,"y":0,"z":0},"maxPos":{"x":0,"y":0,"z":0}},"packable":true,"pixelsToUnit":100,"pivot":{"x":0.5,"y":0.5},"meshType":0}],[0],0,[0],[0],[0]],[[{"name":"1-5","rect":{"x":1,"y":107,"width":248,"height":106},"offset":{"x":0,"y":0},"originalSize":{"width":248,"height":106},"rotated":false,"capInsets":[0,0,0,0],"vertices":{"rawPosition":[],"indexes":[],"uv":[],"nuv":[],"minPos":{"x":0,"y":0,"z":0},"maxPos":{"x":0,"y":0,"z":0}},"packable":true,"pixelsToUnit":100,"pivot":{"x":0.5,"y":0.5},"meshType":0}],[0],0,[0],[0],[0]],[[{"name":"7-6","rect":{"x":253,"y":294,"width":87,"height":96},"offset":{"x":0,"y":0},"originalSize":{"width":87,"height":96},"rotated":true,"capInsets":[0,0,0,0],"vertices":{"rawPosition":[],"indexes":[],"uv":[],"nuv":[],"minPos":{"x":0,"y":0,"z":0},"maxPos":{"x":0,"y":0,"z":0}},"packable":true,"pixelsToUnit":100,"pivot":{"x":0.5,"y":0.5},"meshType":0}],[0],0,[0],[0],[0]],[[{"name":"6-2","rect":{"x":376,"y":202,"width":88,"height":54},"offset":{"x":0,"y":0},"originalSize":{"width":88,"height":54},"rotated":true,"capInsets":[0,0,0,0],"vertices":{"rawPosition":[],"indexes":[],"uv":[],"nuv":[],"minPos":{"x":0,"y":0,"z":0},"maxPos":{"x":0,"y":0,"z":0}},"packable":true,"pixelsToUnit":100,"pivot":{"x":0.5,"y":0.5},"meshType":0}],[0],0,[0],[0],[0]],[[{"name":"2-5","rect":{"x":98,"y":215,"width":153,"height":166},"offset":{"x":0,"y":0},"originalSize":{"width":153,"height":166},"rotated":false,"capInsets":[0,0,0,0],"vertices":{"rawPosition":[],"indexes":[],"uv":[],"nuv":[],"minPos":{"x":0,"y":0,"z":0},"maxPos":{"x":0,"y":0,"z":0}},"packable":true,"pixelsToUnit":100,"pivot":{"x":0.5,"y":0.5},"meshType":0}],[0],0,[0],[0],[0]],[[{"name":"4-2","rect":{"x":313,"y":764,"width":112,"height":89},"offset":{"x":0,"y":0},"originalSize":{"width":112,"height":89},"rotated":true,"capInsets":[0,0,0,0],"vertices":{"rawPosition":[],"indexes":[],"uv":[],"nuv":[],"minPos":{"x":0,"y":0,"z":0},"maxPos":{"x":0,"y":0,"z":0}},"packable":true,"pixelsToUnit":100,"pivot":{"x":0.5,"y":0.5},"meshType":0}],[0],0,[0],[0],[0]],[[{"name":"袋1-2","rect":{"x":297,"y":637,"width":71,"height":125},"offset":{"x":0,"y":0},"originalSize":{"width":71,"height":125},"rotated":false,"capInsets":[0,0,0,0],"vertices":{"rawPosition":[],"indexes":[],"uv":[],"nuv":[],"minPos":{"x":0,"y":0,"z":0},"maxPos":{"x":0,"y":0,"z":0}},"packable":true,"pixelsToUnit":100,"pivot":{"x":0.5,"y":0.5},"meshType":0}],[0],0,[0],[0],[0]],[[{"name":"盲盒","rect":{"x":84,"y":828,"width":119,"height":110},"offset":{"x":0,"y":0},"originalSize":{"width":119,"height":110},"rotated":false,"capInsets":[0,0,0,0],"vertices":{"rawPosition":[],"indexes":[],"uv":[],"nuv":[],"minPos":{"x":0,"y":0,"z":0},"maxPos":{"x":0,"y":0,"z":0}},"packable":true,"pixelsToUnit":100,"pivot":{"x":0.5,"y":0.5},"meshType":0}],[0],0,[0],[0],[0]],[[{"name":"2-2","rect":{"x":94,"y":940,"width":125,"height":169},"offset":{"x":0,"y":0},"originalSize":{"width":125,"height":169},"rotated":false,"capInsets":[0,0,0,0],"vertices":{"rawPosition":[],"indexes":[],"uv":[],"nuv":[],"minPos":{"x":0,"y":0,"z":0},"maxPos":{"x":0,"y":0,"z":0}},"packable":true,"pixelsToUnit":100,"pivot":{"x":0.5,"y":0.5},"meshType":0}],[0],0,[0],[0],[0]],[[{"name":"5-6","rect":{"x":221,"y":979,"width":95,"height":113},"offset":{"x":0,"y":0},"originalSize":{"width":95,"height":113},"rotated":false,"capInsets":[0,0,0,0],"vertices":{"rawPosition":[],"indexes":[],"uv":[],"nuv":[],"minPos":{"x":0,"y":0,"z":0},"maxPos":{"x":0,"y":0,"z":0}},"packable":true,"pixelsToUnit":100,"pivot":{"x":0.5,"y":0.5},"meshType":0}],[0],0,[0],[0],[0]],[[{"name":"1-4","rect":{"x":1,"y":215,"width":253,"height":95},"offset":{"x":0,"y":0},"originalSize":{"width":253,"height":95},"rotated":true,"capInsets":[0,0,0,0],"vertices":{"rawPosition":[],"indexes":[],"uv":[],"nuv":[],"minPos":{"x":0,"y":0,"z":0},"maxPos":{"x":0,"y":0,"z":0}},"packable":true,"pixelsToUnit":100,"pivot":{"x":0.5,"y":0.5},"meshType":0}],[0],0,[0],[0],[0]],[[{"name":"7-5","rect":{"x":434,"y":416,"width":75,"height":74},"offset":{"x":0,"y":0},"originalSize":{"width":75,"height":74},"rotated":true,"capInsets":[0,0,0,0],"vertices":{"rawPosition":[],"indexes":[],"uv":[],"nuv":[],"minPos":{"x":0,"y":0,"z":0},"maxPos":{"x":0,"y":0,"z":0}},"packable":true,"pixelsToUnit":100,"pivot":{"x":0.5,"y":0.5},"meshType":0}],[0],0,[0],[0],[0]],[[{"name":"1-6","rect":{"x":1,"y":1,"width":300,"height":104},"offset":{"x":0,"y":0},"originalSize":{"width":300,"height":104},"rotated":false,"capInsets":[0,0,0,0],"vertices":{"rawPosition":[],"indexes":[],"uv":[],"nuv":[],"minPos":{"x":0,"y":0,"z":0},"maxPos":{"x":0,"y":0,"z":0}},"packable":true,"pixelsToUnit":100,"pivot":{"x":0.5,"y":0.5},"meshType":0}],[0],0,[0],[0],[0]],[[{"name":"4-3","rect":{"x":253,"y":202,"width":121,"height":90},"offset":{"x":0,"y":0},"originalSize":{"width":121,"height":90},"rotated":false,"capInsets":[0,0,0,0],"vertices":{"rawPosition":[],"indexes":[],"uv":[],"nuv":[],"minPos":{"x":0,"y":0,"z":0},"maxPos":{"x":0,"y":0,"z":0}},"packable":true,"pixelsToUnit":100,"pivot":{"x":0.5,"y":0.5},"meshType":0}],[0],0,[0],[0],[0]],[[{"name":"4-5","rect":{"x":221,"y":1094,"width":101,"height":97},"offset":{"x":0,"y":0},"originalSize":{"width":101,"height":97},"rotated":false,"capInsets":[0,0,0,0],"vertices":{"rawPosition":[],"indexes":[],"uv":[],"nuv":[],"minPos":{"x":0,"y":0,"z":0},"maxPos":{"x":0,"y":0,"z":0}},"packable":true,"pixelsToUnit":100,"pivot":{"x":0.5,"y":0.5},"meshType":0}],[0],0,[0],[0],[0]],[[{"name":"3-5","rect":{"x":415,"y":855,"width":100,"height":92},"offset":{"x":0,"y":0},"originalSize":{"width":100,"height":92},"rotated":true,"capInsets":[0,0,0,0],"vertices":{"rawPosition":[],"indexes":[],"uv":[],"nuv":[],"minPos":{"x":0,"y":0,"z":0},"maxPos":{"x":0,"y":0,"z":0}},"packable":true,"pixelsToUnit":100,"pivot":{"x":0.5,"y":0.5},"meshType":0}],[0],0,[0],[0],[0]],[[{"name":"5-4","rect":{"x":313,"y":878,"width":99,"height":100},"offset":{"x":0,"y":0},"originalSize":{"width":99,"height":100},"rotated":true,"capInsets":[0,0,0,0],"vertices":{"rawPosition":[],"indexes":[],"uv":[],"nuv":[],"minPos":{"x":0,"y":0,"z":0},"maxPos":{"x":0,"y":0,"z":0}},"packable":true,"pixelsToUnit":100,"pivot":{"x":0.5,"y":0.5},"meshType":0}],[0],0,[0],[0],[0]],[[{"name":"5-5","rect":{"x":318,"y":979,"width":99,"height":111},"offset":{"x":0,"y":0},"originalSize":{"width":99,"height":111},"rotated":false,"capInsets":[0,0,0,0],"vertices":{"rawPosition":[],"indexes":[],"uv":[],"nuv":[],"minPos":{"x":0,"y":0,"z":0},"maxPos":{"x":0,"y":0,"z":0}},"packable":true,"pixelsToUnit":100,"pivot":{"x":0.5,"y":0.5},"meshType":0}],[0],0,[0],[0],[0]],[[{"name":"2-4","rect":{"x":84,"y":662,"width":137,"height":164},"offset":{"x":0,"y":0},"originalSize":{"width":137,"height":164},"rotated":false,"capInsets":[0,0,0,0],"vertices":{"rawPosition":[],"indexes":[],"uv":[],"nuv":[],"minPos":{"x":0,"y":0,"z":0},"maxPos":{"x":0,"y":0,"z":0}},"packable":true,"pixelsToUnit":100,"pivot":{"x":0.5,"y":0.5},"meshType":0}],[0],0,[0],[0],[0]],[[{"name":"7-2","rect":{"x":419,"y":957,"width":73,"height":75},"offset":{"x":0,"y":0},"originalSize":{"width":73,"height":75},"rotated":false,"capInsets":[0,0,0,0],"vertices":{"rawPosition":[],"indexes":[],"uv":[],"nuv":[],"minPos":{"x":0,"y":0,"z":0},"maxPos":{"x":0,"y":0,"z":0}},"packable":true,"pixelsToUnit":100,"pivot":{"x":0.5,"y":0.5},"meshType":0}],[0],0,[0],[0],[0]],[[{"name":"4-4","rect":{"x":440,"y":128,"width":128,"height":68},"offset":{"x":0,"y":0},"originalSize":{"width":128,"height":68},"rotated":true,"capInsets":[0,0,0,0],"vertices":{"rawPosition":[],"indexes":[],"uv":[],"nuv":[],"minPos":{"x":0,"y":0,"z":0},"maxPos":{"x":0,"y":0,"z":0}},"packable":true,"pixelsToUnit":100,"pivot":{"x":0.5,"y":0.5},"meshType":0}],[0],0,[0],[0],[0]],[[{"name":"3-3","rect":{"x":223,"y":775,"width":88,"height":100},"offset":{"x":0,"y":0},"originalSize":{"width":88,"height":100},"rotated":false,"capInsets":[0,0,0,0],"vertices":{"rawPosition":[],"indexes":[],"uv":[],"nuv":[],"minPos":{"x":0,"y":0,"z":0},"maxPos":{"x":0,"y":0,"z":0}},"packable":true,"pixelsToUnit":100,"pivot":{"x":0.5,"y":0.5},"meshType":0}],[0],0,[0],[0],[0]],[[{"name":"4-1","rect":{"x":415,"y":609,"width":70,"height":93},"offset":{"x":0,"y":0},"originalSize":{"width":70,"height":93},"rotated":true,"capInsets":[0,0,0,0],"vertices":{"rawPosition":[],"indexes":[],"uv":[],"nuv":[],"minPos":{"x":0,"y":0,"z":0},"maxPos":{"x":0,"y":0,"z":0}},"packable":true,"pixelsToUnit":100,"pivot":{"x":0.5,"y":0.5},"meshType":0}],[0],0,[0],[0],[0]],[[{"name":"袋1-1","rect":{"x":382,"y":345,"width":69,"height":126},"offset":{"x":0,"y":0},"originalSize":{"width":69,"height":126},"rotated":true,"capInsets":[0,0,0,0],"vertices":{"rawPosition":[],"indexes":[],"uv":[],"nuv":[],"minPos":{"x":0,"y":0,"z":0},"maxPos":{"x":0,"y":0,"z":0}},"packable":true,"pixelsToUnit":100,"pivot":{"x":0.5,"y":0.5},"meshType":0}],[0],0,[0],[0],[0]],[[{"name":"2-1","rect":{"x":98,"y":383,"width":106,"height":162},"offset":{"x":0,"y":0},"originalSize":{"width":106,"height":162},"rotated":true,"capInsets":[0,0,0,0],"vertices":{"rawPosition":[],"indexes":[],"uv":[],"nuv":[],"minPos":{"x":0,"y":0,"z":0},"maxPos":{"x":0,"y":0,"z":0}},"packable":true,"pixelsToUnit":100,"pivot":{"x":0.5,"y":0.5},"meshType":0}],[0],0,[0],[0],[0]],[[{"name":"1-2","rect":{"x":1,"y":951,"width":222,"height":91},"offset":{"x":0,"y":0},"originalSize":{"width":222,"height":91},"rotated":true,"capInsets":[0,0,0,0],"vertices":{"rawPosition":[],"indexes":[],"uv":[],"nuv":[],"minPos":{"x":0,"y":0,"z":0},"maxPos":{"x":0,"y":0,"z":0}},"packable":true,"pixelsToUnit":100,"pivot":{"x":0.5,"y":0.5},"meshType":0}],[0],0,[0],[0],[0]],[[{"name":"7-1","rect":{"x":324,"y":1167,"width":69,"height":71},"offset":{"x":0,"y":0},"originalSize":{"width":69,"height":71},"rotated":false,"capInsets":[0,0,0,0],"vertices":{"rawPosition":[],"indexes":[],"uv":[],"nuv":[],"minPos":{"x":0,"y":0,"z":0},"maxPos":{"x":0,"y":0,"z":0}},"packable":true,"pixelsToUnit":100,"pivot":{"x":0.5,"y":0.5},"meshType":0}],[0],0,[0],[0],[0]],[[{"name":"6-4","rect":{"x":94,"y":1111,"width":87,"height":62},"offset":{"x":0,"y":0},"originalSize":{"width":87,"height":62},"rotated":false,"capInsets":[0,0,0,0],"vertices":{"rawPosition":[],"indexes":[],"uv":[],"nuv":[],"minPos":{"x":0,"y":0,"z":0},"maxPos":{"x":0,"y":0,"z":0}},"packable":true,"pixelsToUnit":100,"pivot":{"x":0.5,"y":0.5},"meshType":0}],[0],0,[0],[0],[0]],[[{"name":"袋1-6","rect":{"x":303,"y":128,"width":72,"height":135},"offset":{"x":0,"y":0},"originalSize":{"width":72,"height":135},"rotated":true,"capInsets":[0,0,0,0],"vertices":{"rawPosition":[],"indexes":[],"uv":[],"nuv":[],"minPos":{"x":0,"y":0,"z":0},"maxPos":{"x":0,"y":0,"z":0}},"packable":true,"pixelsToUnit":100,"pivot":{"x":0.5,"y":0.5},"meshType":0}],[0],0,[0],[0],[0]],[[{"name":"3-2","rect":{"x":432,"y":258,"width":76,"height":85},"offset":{"x":0,"y":0},"originalSize":{"width":76,"height":85},"rotated":false,"capInsets":[0,0,0,0],"vertices":{"rawPosition":[],"indexes":[],"uv":[],"nuv":[],"minPos":{"x":0,"y":0,"z":0},"maxPos":{"x":0,"y":0,"z":0}},"packable":true,"pixelsToUnit":100,"pivot":{"x":0.5,"y":0.5},"meshType":0}],[0],0,[0],[0],[0]],[[{"name":"3-4","rect":{"x":404,"y":752,"width":92,"height":101},"offset":{"x":0,"y":0},"originalSize":{"width":92,"height":101},"rotated":false,"capInsets":[0,0,0,0],"vertices":{"rawPosition":[],"indexes":[],"uv":[],"nuv":[],"minPos":{"x":0,"y":0,"z":0},"maxPos":{"x":0,"y":0,"z":0}},"packable":true,"pixelsToUnit":100,"pivot":{"x":0.5,"y":0.5},"meshType":0}],[0],0,[0],[0],[0]],[[{"name":"4-6","rect":{"x":221,"y":877,"width":90,"height":100},"offset":{"x":0,"y":0},"originalSize":{"width":90,"height":100},"rotated":false,"capInsets":[0,0,0,0],"vertices":{"rawPosition":[],"indexes":[],"uv":[],"nuv":[],"minPos":{"x":0,"y":0,"z":0},"maxPos":{"x":0,"y":0,"z":0}},"packable":true,"pixelsToUnit":100,"pivot":{"x":0.5,"y":0.5},"meshType":0}],[0],0,[0],[0],[0]],[[{"name":"2-3","rect":{"x":303,"y":1,"width":125,"height":174},"offset":{"x":0,"y":0},"originalSize":{"width":125,"height":174},"rotated":true,"capInsets":[0,0,0,0],"vertices":{"rawPosition":[],"indexes":[],"uv":[],"nuv":[],"minPos":{"x":0,"y":0,"z":0},"maxPos":{"x":0,"y":0,"z":0}},"packable":true,"pixelsToUnit":100,"pivot":{"x":0.5,"y":0.5},"meshType":0}],[0],0,[0],[0],[0]],[[{"name":"袋1-4","rect":{"x":223,"y":637,"width":72,"height":136},"offset":{"x":0,"y":0},"originalSize":{"width":72,"height":136},"rotated":false,"capInsets":[0,0,0,0],"vertices":{"rawPosition":[],"indexes":[],"uv":[],"nuv":[],"minPos":{"x":0,"y":0,"z":0},"maxPos":{"x":0,"y":0,"z":0}},"packable":true,"pixelsToUnit":100,"pivot":{"x":0.5,"y":0.5},"meshType":0}],[0],0,[0],[0],[0]],[[{"name":"3-1","rect":{"x":1,"y":1175,"width":66,"height":115},"offset":{"x":0,"y":0},"originalSize":{"width":66,"height":115},"rotated":true,"capInsets":[0,0,0,0],"vertices":{"rawPosition":[],"indexes":[],"uv":[],"nuv":[],"minPos":{"x":0,"y":0,"z":0},"maxPos":{"x":0,"y":0,"z":0}},"packable":true,"pixelsToUnit":100,"pivot":{"x":0.5,"y":0.5},"meshType":0}],[0],0,[0],[0],[0]],[[{"name":"3-6","rect":{"x":382,"y":493,"width":96,"height":114},"offset":{"x":0,"y":0},"originalSize":{"width":96,"height":114},"rotated":false,"capInsets":[0,0,0,0],"vertices":{"rawPosition":[],"indexes":[],"uv":[],"nuv":[],"minPos":{"x":0,"y":0,"z":0},"maxPos":{"x":0,"y":0,"z":0}},"packable":true,"pixelsToUnit":100,"pivot":{"x":0.5,"y":0.5},"meshType":0}],[0],0,[0],[0],[0]],[[{"name":"7-3","rect":{"x":419,"y":1034,"width":71,"height":73},"offset":{"x":0,"y":0},"originalSize":{"width":71,"height":73},"rotated":true,"capInsets":[0,0,0,0],"vertices":{"rawPosition":[],"indexes":[],"uv":[],"nuv":[],"minPos":{"x":0,"y":0,"z":0},"maxPos":{"x":0,"y":0,"z":0}},"packable":true,"pixelsToUnit":100,"pivot":{"x":0.5,"y":0.5},"meshType":0}],[0],0,[0],[0],[0]],[[{"name":"2-6","rect":{"x":74,"y":491,"width":143,"height":169},"offset":{"x":0,"y":0},"originalSize":{"width":143,"height":169},"rotated":false,"capInsets":[0,0,0,0],"vertices":{"rawPosition":[],"indexes":[],"uv":[],"nuv":[],"minPos":{"x":0,"y":0,"z":0},"maxPos":{"x":0,"y":0,"z":0}},"packable":true,"pixelsToUnit":100,"pivot":{"x":0.5,"y":0.5},"meshType":0}],[0],0,[0],[0],[0]],[[{"name":"7-4","rect":{"x":324,"y":1092,"width":70,"height":73},"offset":{"x":0,"y":0},"originalSize":{"width":70,"height":73},"rotated":false,"capInsets":[0,0,0,0],"vertices":{"rawPosition":[],"indexes":[],"uv":[],"nuv":[],"minPos":{"x":0,"y":0,"z":0},"maxPos":{"x":0,"y":0,"z":0}},"packable":true,"pixelsToUnit":100,"pivot":{"x":0.5,"y":0.5},"meshType":0}],[0],0,[0],[0],[0]],[[{"name":"5-2","rect":{"x":262,"y":383,"width":106,"height":77},"offset":{"x":0,"y":0},"originalSize":{"width":106,"height":77},"rotated":true,"capInsets":[0,0,0,0],"vertices":{"rawPosition":[],"indexes":[],"uv":[],"nuv":[],"minPos":{"x":0,"y":0,"z":0},"maxPos":{"x":0,"y":0,"z":0}},"packable":true,"pixelsToUnit":100,"pivot":{"x":0.5,"y":0.5},"meshType":0}],[0],0,[0],[0],[0]],[[{"name":"6-6","rect":{"x":341,"y":416,"width":73,"height":91},"offset":{"x":0,"y":0},"originalSize":{"width":73,"height":91},"rotated":true,"capInsets":[0,0,0,0],"vertices":{"rawPosition":[],"indexes":[],"uv":[],"nuv":[],"minPos":{"x":0,"y":0,"z":0},"maxPos":{"x":0,"y":0,"z":0}},"packable":true,"pixelsToUnit":100,"pivot":{"x":0.5,"y":0.5},"meshType":0}],[0],0,[0],[0],[0]],[[{"name":"袋1-5","rect":{"x":219,"y":491,"width":88,"height":144},"offset":{"x":0,"y":0},"originalSize":{"width":88,"height":144},"rotated":false,"capInsets":[0,0,0,0],"vertices":{"rawPosition":[],"indexes":[],"uv":[],"nuv":[],"minPos":{"x":0,"y":0,"z":0},"maxPos":{"x":0,"y":0,"z":0}},"packable":true,"pixelsToUnit":100,"pivot":{"x":0.5,"y":0.5},"meshType":0}],[0],0,[0],[0],[0]],[[{"name":"1-1","rect":{"x":1,"y":723,"width":226,"height":81},"offset":{"x":0,"y":0},"originalSize":{"width":226,"height":81},"rotated":true,"capInsets":[0,0,0,0],"vertices":{"rawPosition":[],"indexes":[],"uv":[],"nuv":[],"minPos":{"x":0,"y":0,"z":0},"maxPos":{"x":0,"y":0,"z":0}},"packable":true,"pixelsToUnit":100,"pivot":{"x":0.5,"y":0.5},"meshType":0}],[0],0,[0],[0],[0]],[[{"name":"6-3","rect":{"x":201,"y":1193,"width":72,"height":48},"offset":{"x":0,"y":0},"originalSize":{"width":72,"height":48},"rotated":false,"capInsets":[0,0,0,0],"vertices":{"rawPosition":[],"indexes":[],"uv":[],"nuv":[],"minPos":{"x":0,"y":0,"z":0},"maxPos":{"x":0,"y":0,"z":0}},"packable":true,"pixelsToUnit":100,"pivot":{"x":0.5,"y":0.5},"meshType":0}],[0],0,[0],[0],[0]],[[{"name":"6-5","rect":{"x":118,"y":1175,"width":81,"height":66},"offset":{"x":0,"y":0},"originalSize":{"width":81,"height":66},"rotated":false,"capInsets":[0,0,0,0],"vertices":{"rawPosition":[],"indexes":[],"uv":[],"nuv":[],"minPos":{"x":0,"y":0,"z":0},"maxPos":{"x":0,"y":0,"z":0}},"packable":true,"pixelsToUnit":100,"pivot":{"x":0.5,"y":0.5},"meshType":0}],[0],0,[0],[0],[0]]]]
