[1,["8aC200jsFMNbn016956VCz@6c48a"],["_textureSource"],["cc.SpriteFrame","cc.SpriteAtlas"],0,[[[{"name":"1_07","spriteFrames":["1_07","67UUhuAhlBUL4qRr9DuAAO@2b1a2","1_00","67UUhuAhlBUL4qRr9DuAAO@4b400","1_10","67UUhuAhlBUL4qRr9DuAAO@56a94","1_09","67UUhuAhlBUL4qRr9DuAAO@586f3","1_03","67UUhuAhlBUL4qRr9DuAAO@5bdb8","1_08","67UUhuAhlBUL4qRr9DuAAO@7367b","1_15","67UUhuAhlBUL4qRr9DuAAO@76611","1_04","67UUhuAhlBUL4qRr9DuAAO@81914","1_02","67UUhuAhlBUL4qRr9DuAAO@8c4d1","1_05","67UUhuAhlBUL4qRr9DuAAO@92aaa","1_14","67UUhuAhlBUL4qRr9DuAAO@95bc5","1_16","67UUhuAhlBUL4qRr9DuAAO@9b066","1_11","67UUhuAhlBUL4qRr9DuAAO@b2b09","1_01","67UUhuAhlBUL4qRr9DuAAO@c339a","1_13","67UUhuAhlBUL4qRr9DuAAO@c3e5d","1_06","67UUhuAhlBUL4qRr9DuAAO@dd511","1_12","67UUhuAhlBUL4qRr9DuAAO@e898b"]}],[1],0,[],[],[]],[[{"name":"1_07","rect":{"x":772,"y":354,"width":386,"height":354},"offset":{"x":0,"y":0},"originalSize":{"width":386,"height":354},"rotated":false,"capInsets":[0,0,0,0],"vertices":{"rawPosition":[],"indexes":[],"uv":[],"nuv":[],"minPos":{"x":0,"y":0,"z":0},"maxPos":{"x":0,"y":0,"z":0}},"packable":true,"pixelsToUnit":100,"pivot":{"x":0.5,"y":0.5},"meshType":0}],[0],0,[0],[0],[0]],[[{"name":"1_00","rect":{"x":0,"y":0,"width":386,"height":354},"offset":{"x":0,"y":0},"originalSize":{"width":386,"height":354},"rotated":false,"capInsets":[0,0,0,0],"vertices":{"rawPosition":[],"indexes":[],"uv":[],"nuv":[],"minPos":{"x":0,"y":0,"z":0},"maxPos":{"x":0,"y":0,"z":0}},"packable":true,"pixelsToUnit":100,"pivot":{"x":0.5,"y":0.5},"meshType":0}],[0],0,[0],[0],[0]],[[{"name":"1_10","rect":{"x":0,"y":708,"width":386,"height":354},"offset":{"x":0,"y":0},"originalSize":{"width":386,"height":354},"rotated":false,"capInsets":[0,0,0,0],"vertices":{"rawPosition":[],"indexes":[],"uv":[],"nuv":[],"minPos":{"x":0,"y":0,"z":0},"maxPos":{"x":0,"y":0,"z":0}},"packable":true,"pixelsToUnit":100,"pivot":{"x":0.5,"y":0.5},"meshType":0}],[0],0,[0],[0],[0]],[[{"name":"1_09","rect":{"x":1544,"y":354,"width":386,"height":354},"offset":{"x":0,"y":0},"originalSize":{"width":386,"height":354},"rotated":false,"capInsets":[0,0,0,0],"vertices":{"rawPosition":[],"indexes":[],"uv":[],"nuv":[],"minPos":{"x":0,"y":0,"z":0},"maxPos":{"x":0,"y":0,"z":0}},"packable":true,"pixelsToUnit":100,"pivot":{"x":0.5,"y":0.5},"meshType":0}],[0],0,[0],[0],[0]],[[{"name":"1_03","rect":{"x":1158,"y":0,"width":386,"height":354},"offset":{"x":0,"y":0},"originalSize":{"width":386,"height":354},"rotated":false,"capInsets":[0,0,0,0],"vertices":{"rawPosition":[],"indexes":[],"uv":[],"nuv":[],"minPos":{"x":0,"y":0,"z":0},"maxPos":{"x":0,"y":0,"z":0}},"packable":true,"pixelsToUnit":100,"pivot":{"x":0.5,"y":0.5},"meshType":0}],[0],0,[0],[0],[0]],[[{"name":"1_08","rect":{"x":1158,"y":354,"width":386,"height":354},"offset":{"x":0,"y":0},"originalSize":{"width":386,"height":354},"rotated":false,"capInsets":[0,0,0,0],"vertices":{"rawPosition":[],"indexes":[],"uv":[],"nuv":[],"minPos":{"x":0,"y":0,"z":0},"maxPos":{"x":0,"y":0,"z":0}},"packable":true,"pixelsToUnit":100,"pivot":{"x":0.5,"y":0.5},"meshType":0}],[0],0,[0],[0],[0]],[[{"name":"1_15","rect":{"x":0,"y":1062,"width":386,"height":354},"offset":{"x":0,"y":0},"originalSize":{"width":386,"height":354},"rotated":false,"capInsets":[0,0,0,0],"vertices":{"rawPosition":[],"indexes":[],"uv":[],"nuv":[],"minPos":{"x":0,"y":0,"z":0},"maxPos":{"x":0,"y":0,"z":0}},"packable":true,"pixelsToUnit":100,"pivot":{"x":0.5,"y":0.5},"meshType":0}],[0],0,[0],[0],[0]],[[{"name":"1_04","rect":{"x":1544,"y":0,"width":386,"height":354},"offset":{"x":0,"y":0},"originalSize":{"width":386,"height":354},"rotated":false,"capInsets":[0,0,0,0],"vertices":{"rawPosition":[],"indexes":[],"uv":[],"nuv":[],"minPos":{"x":0,"y":0,"z":0},"maxPos":{"x":0,"y":0,"z":0}},"packable":true,"pixelsToUnit":100,"pivot":{"x":0.5,"y":0.5},"meshType":0}],[0],0,[0],[0],[0]],[[{"name":"1_02","rect":{"x":772,"y":0,"width":386,"height":354},"offset":{"x":0,"y":0},"originalSize":{"width":386,"height":354},"rotated":false,"capInsets":[0,0,0,0],"vertices":{"rawPosition":[],"indexes":[],"uv":[],"nuv":[],"minPos":{"x":0,"y":0,"z":0},"maxPos":{"x":0,"y":0,"z":0}},"packable":true,"pixelsToUnit":100,"pivot":{"x":0.5,"y":0.5},"meshType":0}],[0],0,[0],[0],[0]],[[{"name":"1_05","rect":{"x":0,"y":354,"width":386,"height":354},"offset":{"x":0,"y":0},"originalSize":{"width":386,"height":354},"rotated":false,"capInsets":[0,0,0,0],"vertices":{"rawPosition":[],"indexes":[],"uv":[],"nuv":[],"minPos":{"x":0,"y":0,"z":0},"maxPos":{"x":0,"y":0,"z":0}},"packable":true,"pixelsToUnit":100,"pivot":{"x":0.5,"y":0.5},"meshType":0}],[0],0,[0],[0],[0]],[[{"name":"1_14","rect":{"x":1544,"y":708,"width":386,"height":354},"offset":{"x":0,"y":0},"originalSize":{"width":386,"height":354},"rotated":false,"capInsets":[0,0,0,0],"vertices":{"rawPosition":[],"indexes":[],"uv":[],"nuv":[],"minPos":{"x":0,"y":0,"z":0},"maxPos":{"x":0,"y":0,"z":0}},"packable":true,"pixelsToUnit":100,"pivot":{"x":0.5,"y":0.5},"meshType":0}],[0],0,[0],[0],[0]],[[{"name":"1_16","rect":{"x":386,"y":1062,"width":386,"height":354},"offset":{"x":0,"y":0},"originalSize":{"width":386,"height":354},"rotated":false,"capInsets":[0,0,0,0],"vertices":{"rawPosition":[],"indexes":[],"uv":[],"nuv":[],"minPos":{"x":0,"y":0,"z":0},"maxPos":{"x":0,"y":0,"z":0}},"packable":true,"pixelsToUnit":100,"pivot":{"x":0.5,"y":0.5},"meshType":0}],[0],0,[0],[0],[0]],[[{"name":"1_11","rect":{"x":386,"y":708,"width":386,"height":354},"offset":{"x":0,"y":0},"originalSize":{"width":386,"height":354},"rotated":false,"capInsets":[0,0,0,0],"vertices":{"rawPosition":[],"indexes":[],"uv":[],"nuv":[],"minPos":{"x":0,"y":0,"z":0},"maxPos":{"x":0,"y":0,"z":0}},"packable":true,"pixelsToUnit":100,"pivot":{"x":0.5,"y":0.5},"meshType":0}],[0],0,[0],[0],[0]],[[{"name":"1_01","rect":{"x":386,"y":0,"width":386,"height":354},"offset":{"x":0,"y":0},"originalSize":{"width":386,"height":354},"rotated":false,"capInsets":[0,0,0,0],"vertices":{"rawPosition":[],"indexes":[],"uv":[],"nuv":[],"minPos":{"x":0,"y":0,"z":0},"maxPos":{"x":0,"y":0,"z":0}},"packable":true,"pixelsToUnit":100,"pivot":{"x":0.5,"y":0.5},"meshType":0}],[0],0,[0],[0],[0]],[[{"name":"1_13","rect":{"x":1158,"y":708,"width":386,"height":354},"offset":{"x":0,"y":0},"originalSize":{"width":386,"height":354},"rotated":false,"capInsets":[0,0,0,0],"vertices":{"rawPosition":[],"indexes":[],"uv":[],"nuv":[],"minPos":{"x":0,"y":0,"z":0},"maxPos":{"x":0,"y":0,"z":0}},"packable":true,"pixelsToUnit":100,"pivot":{"x":0.5,"y":0.5},"meshType":0}],[0],0,[0],[0],[0]],[[{"name":"1_06","rect":{"x":386,"y":354,"width":386,"height":354},"offset":{"x":0,"y":0},"originalSize":{"width":386,"height":354},"rotated":false,"capInsets":[0,0,0,0],"vertices":{"rawPosition":[],"indexes":[],"uv":[],"nuv":[],"minPos":{"x":0,"y":0,"z":0},"maxPos":{"x":0,"y":0,"z":0}},"packable":true,"pixelsToUnit":100,"pivot":{"x":0.5,"y":0.5},"meshType":0}],[0],0,[0],[0],[0]],[[{"name":"1_12","rect":{"x":772,"y":708,"width":386,"height":354},"offset":{"x":0,"y":0},"originalSize":{"width":386,"height":354},"rotated":false,"capInsets":[0,0,0,0],"vertices":{"rawPosition":[],"indexes":[],"uv":[],"nuv":[],"minPos":{"x":0,"y":0,"z":0},"maxPos":{"x":0,"y":0,"z":0}},"packable":true,"pixelsToUnit":100,"pivot":{"x":0.5,"y":0.5},"meshType":0}],[0],0,[0],[0],[0]]]]
